jerryExcel/__init__.py
jerryExcel-1.0.1.dist-info/LICENSE
jerryExcel-1.0.1.dist-info/METADATA
jerryExcel-1.0.1.dist-info/WHEEL
jerryExcel-1.0.1.dist-info/top_level.txt
jerryExcel-1.0.1.dist-info/RECORD
