Metadata-Version: 2.1
Name: jerryExcel
Version: 1.0.1
Summary: A tool for excel
Home-page: https://github.com/JeansLaw/excelUtil.git
Author: JerryLaw
Author-email: 623487850@qq.com
License: UNKNOWN
Platform: UNKNOWN
Classifier: Programming Language :: Python :: 3
Classifier: License :: OSI Approved :: MIT License
Classifier: Operating System :: OS Independent
Requires-Dist: xlrd
Requires-Dist: xlutils
Requires-Dist: xlwt
